{
  "chapter2_items": [
    {
      "idx": 1,
      "chapter": 2,
      "name_en": "PORK BELLY SAMGYUPSAL (SKIN ON)",
      "cut_method": "CLEAN CUT - MACHINE",
      "size": "1 CM",
      "plu": "9207",
      "bestseller": true,
      "category": "삼겹살/수육",
      "species": "돼지"
    },
    {
      "idx": 2,
      "chapter": 2,
      "name_en": "PORK BELLY SUYOOK (SKIN ON)",
      "cut_method": "CLEAN CUT - MACHINE",
      "size": "3 CM",
      "plu": "9921",
      "bestseller": true,
      "category": "삼겹살/수육",
      "species": "돼지"
    },
    {
      "idx": 3,
      "chapter": 2,
      "name_en": "PORK BELLY CROSS CUT (SKINLESS)",
      "cut_method": "CROSS CUT",
      "size": "4 MM",
      "plu": "9923",
      "bestseller": true,
      "category": "삼겹살/수육",
      "species": "돼지"
    },
    {
      "idx": 4,
      "chapter": 2,
      "name_en": "PORK BELLY ROLL (SKINLESS)",
      "cut_method": "HONEYCOMB",
      "size": "1.5 CM",
      "plu": "9303",
      "bestseller": false,
      "category": "삼겹살/수육",
      "species": "돼지"
    },
    {
      "idx": 5,
      "chapter": 2,
      "name_en": "PORK BELLY FLOWER CUT",
      "cut_method": "CLEAN CUT - MACHINE",
      "size": "4 MM",
      "plu": "",
      "bestseller": true,
      "category": "삼겹살/수육",
      "species": "돼지"
    },
    {
      "idx": 6,
      "chapter": 2,
      "name_en": "PORK BELLY FLAT (SKINLESS)",
      "cut_method": "CLEAN CUT - MACHINE",
      "size": "1 CM",
      "plu": "9207",
      "bestseller": false,
      "category": "삼겹살/수육",
      "species": "돼지"
    },
    {
      "idx": 7,
      "chapter": 2,
      "name_en": "PORK BELLY HALF CUT",
      "cut_method": "CLEAN CUT - MACHINE",
      "size": "1.5/1 CM",
      "plu": "9304",
      "bestseller": false,
      "category": "삼겹살/수육",
      "species": "돼지"
    },
    {
      "idx": 8,
      "chapter": 2,
      "name_en": "PORK BELLY SUYOOK (SKINLESS)",
      "cut_method": "CLEAN CUT - MACHINE",
      "size": "3 CM",
      "plu": "9924",
      "bestseller": false,
      "category": "삼겹살/수육",
      "species": "돼지"
    },
    {
      "idx": 9,
      "chapter": 2,
      "name_en": "PORK BELLY SHABU - FLAT",
      "cut_method": "CLEAN CUT - MACHINE",
      "size": "2 MM",
      "plu": "9922",
      "bestseller": true,
      "category": "삼겹살/수육",
      "species": "돼지"
    },
    {
      "idx": 10,
      "chapter": 2,
      "name_en": "PORK BELLY SHABU - ROLL",
      "cut_method": "CLEAN CUT - MACHINE",
      "size": "2 MM",
      "plu": "9302",
      "bestseller": false,
      "category": "삼겹살/수육",
      "species": "돼지"
    },
    {
      "idx": 11,
      "chapter": 2,
      "name_en": "BONELESS PORK SHOULDER STEAK",
      "cut_method": "THICK CUT",
      "size": "1.5 CM",
      "plu": "9212",
      "bestseller": true,
      "category": "목살/등심/기타",
      "species": "돼지"
    },
    {
      "idx": 12,
      "chapter": 2,
      "name_en": "SPECIAL PORK SHOULDER SET",
      "cut_method": "REG - HONEY",
      "size": "1.5 CM",
      "plu": "9221",
      "bestseller": true,
      "category": "목살/등심/기타",
      "species": "돼지"
    },
    {
      "idx": 13,
      "chapter": 2,
      "name_en": "SPECIAL PORK SHOULDER & BELLY",
      "cut_method": "REG - HONEY",
      "size": "1.5 CM",
      "plu": "9222",
      "bestseller": false,
      "category": "목살/등심/기타",
      "species": "돼지"
    },
    {
      "idx": 14,
      "chapter": 2,
      "name_en": "MIXED PORK FOR SOUP",
      "cut_method": "CHOP",
      "size": "2~3 CM",
      "plu": "9206",
      "bestseller": false,
      "category": "목살/등심/기타",
      "species": "돼지"
    },
    {
      "idx": 15,
      "chapter": 2,
      "name_en": "PORK GALBI / HONEYCOMB",
      "cut_method": "HONEYCOMB",
      "size": "1.5 CM",
      "plu": "9220",
      "bestseller": true,
      "category": "목살/등심/기타",
      "species": "돼지"
    },
    {
      "idx": 16,
      "chapter": 2,
      "name_en": "PORK SHOULDER SHABU",
      "cut_method": "CLEAN CUT - MACHINE",
      "size": "2 MM",
      "plu": "9313",
      "bestseller": false,
      "category": "목살/등심/기타",
      "species": "돼지"
    },
    {
      "idx": 17,
      "chapter": 2,
      "name_en": "PORK SHANK STEAK (BONE IN)",
      "cut_method": "CLEAN CUT - MACHINE",
      "size": "1.5 CM",
      "plu": "9230",
      "bestseller": false,
      "category": "목살/등심/기타",
      "species": "돼지"
    },
    {
      "idx": 18,
      "chapter": 2,
      "name_en": "PORK JOWL - HANGJEONG (항정살)",
      "cut_method": "REG",
      "size": "1 CM",
      "plu": "9158",
      "bestseller": true,
      "category": "목살/등심/기타",
      "species": "돼지"
    },
    {
      "idx": 19,
      "chapter": 2,
      "name_en": "PORK JOWL - MARBLING",
      "cut_method": "REG - CURVE",
      "size": "0.5 MM",
      "plu": "9159",
      "bestseller": true,
      "category": "목살/등심/기타",
      "species": "돼지"
    },
    {
      "idx": 20,
      "chapter": 2,
      "name_en": "SPECIAL SET - PORK JOWL",
      "cut_method": "ASSORTED",
      "size": "0.5 MM",
      "plu": "9160",
      "bestseller": false,
      "category": "목살/등심/기타",
      "species": "돼지"
    },
    {
      "idx": 21,
      "chapter": 2,
      "name_en": "PORK LOIN BONELESS (KATSU)",
      "cut_method": "KATSU CUT",
      "size": "1.5 CM",
      "plu": "9224",
      "bestseller": false,
      "category": "목살/등심/기타",
      "species": "돼지"
    },
    {
      "idx": 22,
      "chapter": 2,
      "name_en": "PORK LOIN SHABU ROLL",
      "cut_method": "CLEAN CUT - MACHINE",
      "size": "2 MM",
      "plu": "9227",
      "bestseller": false,
      "category": "목살/등심/기타",
      "species": "돼지"
    },
    {
      "idx": 23,
      "chapter": 2,
      "name_en": "MIXED PORK GROUND",
      "cut_method": "GROUND",
      "size": "GROUND",
      "plu": "9915",
      "bestseller": false,
      "category": "목살/등심/기타",
      "species": "돼지"
    },
    {
      "idx": 24,
      "chapter": 2,
      "name_en": "PORK BABY BACK RIB CUT",
      "cut_method": "CLEAN CUT",
      "size": "",
      "plu": "9319",
      "bestseller": true,
      "category": "갈비/뼈류",
      "species": "돼지"
    },
    {
      "idx": 25,
      "chapter": 2,
      "name_en": "PORK BABY BACK RIBS - CHAIN",
      "cut_method": "CLEAN CUT - MACHINE",
      "size": "3 CM",
      "plu": "9928",
      "bestseller": false,
      "category": "갈비/뼈류",
      "species": "돼지"
    },
    {
      "idx": 26,
      "chapter": 2,
      "name_en": "PORK BABY BACK RIBS - WHOLE",
      "cut_method": "WHOLE / SKIN OUT",
      "size": "",
      "plu": "",
      "bestseller": false,
      "category": "갈비/뼈류",
      "species": "돼지"
    },
    {
      "idx": 27,
      "chapter": 2,
      "name_en": "PORK SPARE RIB CUT",
      "cut_method": "CLEAN CUT",
      "size": "",
      "plu": "9326",
      "bestseller": false,
      "category": "갈비/뼈류",
      "species": "돼지"
    },
    {
      "idx": 28,
      "chapter": 2,
      "name_en": "PORK NECK BONE",
      "cut_method": "CLEAN CUT - MACHINE",
      "size": "5 CM",
      "plu": "9311",
      "bestseller": false,
      "category": "갈비/뼈류",
      "species": "돼지"
    },
    {
      "idx": 29,
      "chapter": 2,
      "name_en": "PORK FRONT FEET",
      "cut_method": "CLEAN CUT - MACHINE",
      "size": "5 CM",
      "plu": "9306",
      "bestseller": false,
      "category": "갈비/뼈류",
      "species": "돼지"
    },
    {
      "idx": 30,
      "chapter": 2,
      "name_en": "PORK HOCK",
      "cut_method": "CLEAN CUT - MACHINE",
      "size": "WHOLE",
      "plu": "9316",
      "bestseller": false,
      "category": "갈비/뼈류",
      "species": "돼지"
    },
    {
      "idx": 31,
      "chapter": 2,
      "name_en": "PORK BONE - FEMUR (SOUP)",
      "cut_method": "CLEAN CUT - MACHINE",
      "size": "5 CM",
      "plu": "9317",
      "bestseller": false,
      "category": "갈비/뼈류",
      "species": "돼지"
    },
    {
      "idx": 32,
      "chapter": 2,
      "name_en": "BEEF RIBEYE THIN - BULGOGI",
      "cut_method": "CLEAN CUT - MACHINE",
      "size": "2 MM",
      "plu": "9203",
      "bestseller": true,
      "category": "등심/차돌박이",
      "species": "소"
    },
    {
      "idx": 33,
      "chapter": 2,
      "name_en": "BEEF RIBEYE SHABU",
      "cut_method": "CLEAN CUT - MACHINE",
      "size": "2 MM",
      "plu": "9106",
      "bestseller": true,
      "category": "등심/차돌박이",
      "species": "소"
    },
    {
      "idx": 34,
      "chapter": 2,
      "name_en": "BEEF RIBEYE SAEWOO",
      "cut_method": "SHRIMP CUT",
      "size": "",
      "plu": "9216",
      "bestseller": false,
      "category": "등심/차돌박이",
      "species": "소"
    },
    {
      "idx": 35,
      "chapter": 2,
      "name_en": "BEEF RIBEYE STEAK",
      "cut_method": "STEAK CUT",
      "size": "1.5 CM",
      "plu": "9138",
      "bestseller": true,
      "category": "등심/차돌박이",
      "species": "소"
    },
    {
      "idx": 36,
      "chapter": 2,
      "name_en": "SPECIAL BEEF SET",
      "cut_method": "ASSORTED",
      "size": "0.5 CM",
      "plu": "9171",
      "bestseller": true,
      "category": "등심/차돌박이",
      "species": "소"
    },
    {
      "idx": 37,
      "chapter": 2,
      "name_en": "BEEF BRISKET SHABU (FLAT)",
      "cut_method": "CLEAN CUT - MACHINE",
      "size": "2 MM",
      "plu": "9162",
      "bestseller": true,
      "category": "등심/차돌박이",
      "species": "소"
    },
    {
      "idx": 38,
      "chapter": 2,
      "name_en": "BEEF BRISKET SHABU (ROLL)",
      "cut_method": "CLEAN CUT - MACHINE",
      "size": "2 MM",
      "plu": "9163",
      "bestseller": true,
      "category": "등심/차돌박이",
      "species": "소"
    },
    {
      "idx": 39,
      "chapter": 2,
      "name_en": "BEEF BRISKET STEAK",
      "cut_method": "STEAK CUT",
      "size": "1.5 CM",
      "plu": "9164",
      "bestseller": false,
      "category": "등심/차돌박이",
      "species": "소"
    },
    {
      "idx": 40,
      "chapter": 2,
      "name_en": "BEEF BRISKET WHOLE",
      "cut_method": "WHOLE",
      "size": "",
      "plu": "9166",
      "bestseller": false,
      "category": "등심/차돌박이",
      "species": "소"
    },
    {
      "idx": 41,
      "chapter": 2,
      "name_en": "BEEF NAVEL SHABU",
      "cut_method": "CLEAN CUT - MACHINE",
      "size": "2 MM",
      "plu": "9127",
      "bestseller": true,
      "category": "등심/차돌박이",
      "species": "소"
    },
    {
      "idx": 42,
      "chapter": 2,
      "name_en": "BEEF NAVEL STEAK",
      "cut_method": "THICK SLICED",
      "size": "1.5 CM",
      "plu": "9168",
      "bestseller": false,
      "category": "등심/차돌박이",
      "species": "소"
    },
    {
      "idx": 43,
      "chapter": 2,
      "name_en": "BEEF CHUCK TOP BLADE STEAK",
      "cut_method": "STEAK CUT",
      "size": "1.5 CM",
      "plu": "9153",
      "bestseller": true,
      "category": "목심/우둔/기타",
      "species": "소"
    },
    {
      "idx": 44,
      "chapter": 2,
      "name_en": "BEEF CHUCK TOP BLADE SHABU",
      "cut_method": "CLEAN CUT - MACHINE",
      "size": "2 MM",
      "plu": "",
      "bestseller": false,
      "category": "목심/우둔/기타",
      "species": "소"
    },
    {
      "idx": 45,
      "chapter": 2,
      "name_en": "BEEF CHUCK FLAP TAIL (살치살)",
      "cut_method": "GALBISAL CUT",
      "size": "0.5 CM",
      "plu": "9202",
      "bestseller": true,
      "category": "목심/우둔/기타",
      "species": "소"
    },
    {
      "idx": 46,
      "chapter": 2,
      "name_en": "BEEF CHUCK FLAP STEAK",
      "cut_method": "STEAK CUT",
      "size": "1.5 CM",
      "plu": "",
      "bestseller": false,
      "category": "목심/우둔/기타",
      "species": "소"
    },
    {
      "idx": 47,
      "chapter": 2,
      "name_en": "BEEF EYE ROUND STEAK",
      "cut_method": "STEAK CUT",
      "size": "1.5 CM",
      "plu": "9170",
      "bestseller": false,
      "category": "목심/우둔/기타",
      "species": "소"
    },
    {
      "idx": 48,
      "chapter": 2,
      "name_en": "BEEF EYE ROUND SHABU",
      "cut_method": "CLEAN CUT - MACHINE",
      "size": "2 MM",
      "plu": "",
      "bestseller": false,
      "category": "목심/우둔/기타",
      "species": "소"
    },
    {
      "idx": 49,
      "chapter": 2,
      "name_en": "BEEF SKIRT STEAK",
      "cut_method": "STEAK CUT",
      "size": "1.5 CM",
      "plu": "9134",
      "bestseller": true,
      "category": "목심/우둔/기타",
      "species": "소"
    },
    {
      "idx": 50,
      "chapter": 2,
      "name_en": "BEEF SKIRT SHABU",
      "cut_method": "CLEAN CUT - MACHINE",
      "size": "2 MM",
      "plu": "",
      "bestseller": false,
      "category": "목심/우둔/기타",
      "species": "소"
    },
    {
      "idx": 51,
      "chapter": 2,
      "name_en": "BEEF SHORT RIB 3-BONE (LA GALBI)",
      "cut_method": "CLEAN CUT - MACHINE",
      "size": "",
      "plu": "9205",
      "bestseller": true,
      "category": "LA갈비/탕류 뼈",
      "species": "소"
    },
    {
      "idx": 52,
      "chapter": 2,
      "name_en": "BEEF SHORT RIB BONE (SOUP)",
      "cut_method": "CLEAN CUT - MACHINE",
      "size": "",
      "plu": "9156",
      "bestseller": false,
      "category": "LA갈비/탕류 뼈",
      "species": "소"
    },
    {
      "idx": 53,
      "chapter": 2,
      "name_en": "BONELESS BEEF SHORT RIB (갈비살)",
      "cut_method": "3~4 BONE MEAT",
      "size": "0.5 CM",
      "plu": "9215",
      "bestseller": true,
      "category": "LA갈비/탕류 뼈",
      "species": "소"
    },
    {
      "idx": 54,
      "chapter": 2,
      "name_en": "BEEF SHORT RIB FOR STEW",
      "cut_method": "CLEAN CUT - MACHINE",
      "size": "",
      "plu": "9149",
      "bestseller": false,
      "category": "LA갈비/탕류 뼈",
      "species": "소"
    },
    {
      "idx": 55,
      "chapter": 2,
      "name_en": "BEEF BACK RIB",
      "cut_method": "",
      "size": "",
      "plu": "9167",
      "bestseller": false,
      "category": "LA갈비/탕류 뼈",
      "species": "소"
    },
    {
      "idx": 56,
      "chapter": 2,
      "name_en": "BEEF CHUCK SHORT RIB W/BONE",
      "cut_method": "4 BONES",
      "size": "",
      "plu": "",
      "bestseller": false,
      "category": "LA갈비/탕류 뼈",
      "species": "소"
    },
    {
      "idx": 57,
      "chapter": 2,
      "name_en": "BEEF CHUCK SHORT RIB (STEW)",
      "cut_method": "CLEAN CUT - MACHINE",
      "size": "",
      "plu": "9161",
      "bestseller": false,
      "category": "LA갈비/탕류 뼈",
      "species": "소"
    },
    {
      "idx": 58,
      "chapter": 2,
      "name_en": "BEEF CHUCK SHORT RIB BONELESS",
      "cut_method": "4 BONES",
      "size": "0.5 CM",
      "plu": "9219",
      "bestseller": true,
      "category": "LA갈비/탕류 뼈",
      "species": "소"
    },
    {
      "idx": 59,
      "chapter": 2,
      "name_en": "BEEF GROUND",
      "cut_method": "MACHINE GROUND",
      "size": "",
      "plu": "9914",
      "bestseller": false,
      "category": "LA갈비/탕류 뼈",
      "species": "소"
    },
    {
      "idx": 60,
      "chapter": 2,
      "name_en": "MIXED BEEF FOR SOUP",
      "cut_method": "HAND SPECIAL",
      "size": "",
      "plu": "9137",
      "bestseller": false,
      "category": "LA갈비/탕류 뼈",
      "species": "소"
    }
  ],
  "chapter3_premium": [
    {
      "idx": 1,
      "chapter": 3,
      "name_en": "Hanger Steak, Cleaned",
      "name_kr": "토시살",
      "spec": "\"Peeled/Denuded\" — Membrane must be fully removed before delivery.",
      "margin": "★★★",
      "premium": true
    },
    {
      "idx": 2,
      "chapter": 3,
      "name_en": "Shoulder Tender (Teres Major)",
      "name_kr": "제비추리",
      "spec": "\"Whole\" form only. Do NOT accept pre-sliced.",
      "margin": "★★★",
      "premium": true
    },
    {
      "idx": 3,
      "chapter": 3,
      "name_en": "Inside Skirt Steak, Peeled",
      "name_kr": "안창살",
      "spec": "INSIDE skirt only — not Outside. Inside = correct Korean Anchangsal.",
      "margin": "★★★",
      "premium": true
    },
    {
      "idx": 4,
      "chapter": 3,
      "name_en": "Beef Flap Meat (Sirloin Flap)",
      "name_kr": "치마살",
      "spec": "\"Peeled\" required. Without this spec, yield loss reaches 40%.",
      "margin": "★★★",
      "premium": true
    },
    {
      "idx": 5,
      "chapter": 3,
      "name_en": "Chuck Flap Tail",
      "name_kr": "살치살",
      "spec": "PRIME GRADE required. Choice grade = reject for grilling use.",
      "margin": "★★★",
      "premium": true
    },
    {
      "idx": 6,
      "chapter": 3,
      "name_en": "Flat Iron (Top Blade)",
      "name_kr": "부채살",
      "spec": "Must be separated from Shoulder Clod. Verify clean seam.",
      "margin": "★★☆",
      "premium": true
    },
    {
      "idx": 7,
      "chapter": 3,
      "name_en": "Rib Fingers (Intercostal)",
      "name_kr": "늙간살",
      "spec": "\"Peeled\" — membrane and bone-side tissue fully removed.",
      "margin": "★★☆",
      "premium": true
    },
    {
      "idx": 8,
      "chapter": 3,
      "name_en": "Short Plate (Beef Belly)",
      "name_kr": "업진살",
      "spec": "\"Boneless\" and \"Trimmed\" — verify both specs on every delivery.",
      "margin": "★★☆",
      "premium": true
    },
    {
      "idx": 9,
      "chapter": 3,
      "name_en": "Ribeye Cap (Spinalis)",
      "name_kr": "새우살",
      "spec": "\"Deckle-off\" Spinalis only. Highest margin item.",
      "margin": "★★★",
      "premium": true
    },
    {
      "idx": 10,
      "chapter": 3,
      "name_en": "Ribeye Roll, Export Style",
      "name_kr": "알등심",
      "spec": "\"Lip-off\" required. Lip-on = excess fat = waste.",
      "margin": "★★☆",
      "premium": true
    },
    {
      "idx": 11,
      "chapter": 3,
      "name_en": "Eye of Round",
      "name_kr": "홍두깨살",
      "spec": "\"Denuded\" — all external fat must be removed.",
      "margin": "★★☆",
      "premium": true
    },
    {
      "idx": 12,
      "chapter": 3,
      "name_en": "Lifter Meat (Blade Meat)",
      "name_kr": "꽃등심덧살",
      "spec": "⚠️ Do NOT confuse with Ribeye Cap. Different cut, different price.",
      "margin": "★☆☆",
      "premium": true
    }
  ],
  "summary": {
    "chapter2_count": 60,
    "chapter3_count": 12,
    "chapter2_bestsellers": 24
  }
}